<?xml version="1.0" encoding="UTF-8"?>

<features name="config-${project.version}" xmlns="http://karaf.apache.org/xmlns/features/v1.2.0"
          xmlns:xsi="http://www.w3.org/2001/XMLSchema-instance"
          xsi:schemaLocation="http://karaf.apache.org/xmlns/features/v1.2.0 http://karaf.apache.org/xmlns/features/v1.2.0">
  <feature name='config-all' version='${project.version}'>
    <feature version='${project.version}'>odl-config-subsystem</feature>
  </feature>

  <feature name='odl-config-subsystem' version='${project.version}'>
    <feature version='${yangtools.version}'>yangtools-concepts</feature>
    <feature version='${yangtools.version}'>yangtools-binding</feature>
    <feature version='${yangtools.version}'>yangtools-binding-generator</feature>
    <feature version='${mdsal.version}'>odl-mdsal-commons</feature>
    <bundle>mvn:org.opendaylight.controller/config-api/${project.version}</bundle>
    <bundle>mvn:org.opendaylight.controller/config-util/${project.version}</bundle>
    <bundle>mvn:org.opendaylight.controller/config-manager/${project.version}</bundle>
    <bundle>mvn:org.opendaylight.controller/yang-jmx-generator/${project.version}</bundle>
    <bundle>mvn:org.opendaylight.controller/config-persister-api/${project.version}</bundle>
    <bundle>mvn:org.opendaylight.controller/config-persister-file-xml-adapter/${project.version}</bundle>
    <bundle>mvn:org.opendaylight.controller/config-persister-directory-xml-adapter/${project.version}</bundle>
    <bundle>mvn:org.opendaylight.controller/shutdown-api/${project.version}</bundle>
    <bundle>mvn:org.opendaylight.controller/shutdown-impl/${project.version}</bundle>
    <bundle>mvn:org.osgi/org.osgi.core/${osgi.core.version}</bundle>
    <bundle>wrap:mvn:com.google.guava/guava/${guava.version}</bundle>
    <bundle>mvn:org.javassist/javassist/${javassist.version}</bundle>
  </feature>
</features>